{"url": "radaronline.com/exclusives/2017/10/dwts-vanessa-lachey-nick-eliminated-wardrobe-malfuction-planned/", "text": "According to a source backstage, \"Vanessa's dance last night was flawless, but her skirt ripping off was totally staged!\"\n\n\"She is so thirsty to win now that she is willing to do anything to stay on air.\n\nShe isn't stupid. Before Vanessa was a celebrity in her own right, she was an entertainment new reporter, so she definitely knows how to make headlines.\"\n\n\"Vanessa is loving the attention she is getting right now,\" the insider added to Radar.", "images": ["https://radaronline.com/radar_logo_neon.png", "https://radaronline.com/radar_logo.png", "https://radaronline.com/newsletter_icon.png", "https://radaronline.com/icons/email_black.svg", "https://radaronline.com/icons/twitter_black.svg", "https://media.radaronline.com/brand-img/xGskFOWJm/1200x628/2017/10/DWTS-Vanessa-Lachey-Wardrobe-Malfunction-pp.jpg", "https://radaronline.com/icons/facebook_black.svg", "https://radaronline.com/radar_tip.png"], "top_img": "https://media.radaronline.com/brand-img/xGskFOWJm/1200x628/2017/10/DWTS-Vanessa-Lachey-Wardrobe-Malfunction-pp.jpg", "keywords": [], "authors": ["Radar Staff"], "canonical_link": "https://radaronline.com/videos/dwts-vanessa-lachey-nick-eliminated-wardrobe-malfuction-planned/", "title": "'DWTS' Fakery: Vanessa Lachey 'Staged' Wardrobe Malfunction!", "meta_data": {"viewport": "width=device-width,initial-scale=1,shrink-to-fit=no", "theme-color": "#666", "description": "'DWTS' diva Vanessa Lachey's wardrobe malfunction may not have been a malfunction after all.", "robots": "max-snippet:-1, max-image-preview:large, max-video-preview:-1", "keywords": "VIDEOS,REALITY TV", "og": {"site_name": "RadarOnline", "title": "'DWTS' Fakery: Vanessa Lachey 'Staged' Wardrobe Malfunction!", "url": "https://radaronline.com/videos/dwts-vanessa-lachey-nick-eliminated-wardrobe-malfuction-planned/", "description": "'DWTS' diva Vanessa Lachey's wardrobe malfunction may not have been a malfunction after all.", "type": "article", "locale": "en_US", "image": {"identifier": "https://media.radaronline.com/brand-img/xGskFOWJm/1200x628/2017/10/DWTS-Vanessa-Lachey-Wardrobe-Malfunction-pp.jpg", "width": 1200, "height": 628, "type": "image/jpeg", "alt": "//DWTS Vanessa Lachey Wardrobe Malfunction pp"}}, "article": {"published_time": "2017-10-24T20:47:17.000Z", "modified_time": "2018-03-22T21:23:55.000Z", "author": "Radar Staff"}, "twitter": {"site": "https://twitter.com/radar_online/", "card": "summary_large_image", "title": "'DWTS' Fakery: Vanessa Lachey 'Staged' Wardrobe Malfunction!", "description": "'DWTS' diva Vanessa Lachey's wardrobe malfunction may not have been a malfunction after all.", "image": {"identifier": "https://media.radaronline.com/brand-img/xGskFOWJm/1200x628/2017/10/DWTS-Vanessa-Lachey-Wardrobe-Malfunction-pp.jpg", "alt": "//DWTS Vanessa Lachey Wardrobe Malfunction pp"}}}, "movies": [], "publish_date": 1508878037.0, "source": "http://radaronline.com", "summary": ""}