{"url": "http://disney.trendolizer.com/2017/08/disney-channel-battle-vote-in-round-2-for-your-favorite-tv-series.html", "text": "About Trendolizer\u2122\n\nTrendolizer\u2122 (patent pending) automatically scans the internet for trending content. The website you are looking at has no human editors at all: links to trending stories are automatically posted from a selection of the data Trendolizer\u2122 picked up. If you are interested in using the Trendolizer\u2122 engine, dashboard or API for your own projects, more information is available at get.trendolizer.com . Trendolizer\u2122 is owned by Lead Stories LLC.\n\nPrivacy policy\n\nThis site uses cookies to track user behaviour on this site, without linking to personally identifiable data. Advertisers may also use cookies, but the scope and nature of this use is beyond our control.", "images": ["http://disney.trendolizer.com/images/288xNxcaption_14914683.jpg.pagespeed.ic.keN_qQjACS.jpg", "http://disney.trendolizer.com/images/288xNxcaption_14916465.jpg.pagespeed.ic.YfrrSni68D.jpg", "http://disney.trendolizer.com/images/288xNxcaption_14913574.jpg.pagespeed.ic.-1KqhLssNn.jpg", "http://disney.trendolizer.com/images/288xNxcaption_14909036.jpg.pagespeed.ic.ySe8LsiNZK.jpg", "http://disney.trendolizer.com/images/288xNxcaption_14916000.jpg.pagespeed.ic.W5fMgT7I6I.jpg", "http://disney.trendolizer.com/images/288xNxcaption_14909869.jpg.pagespeed.ic.9GFnZQgjQX.jpg", "http://akns-images.eonline.com/eol_images/Entire_Site/2017721/rs_600x600-170821073613-600DIsney_MK08217.jpg?downsize=450:*&crop=450:350;left,top", "http://disney.trendolizer.com/images/caption_6898871.jpg", "http://disney.trendolizer.com/images/288xNxcaption_14903412.jpg.pagespeed.ic.q9vUIhYJqi.jpg", "http://disney.trendolizer.com/images/288xNxcaption_14915239.jpg.pagespeed.ic.J8Qkst9zwX.jpg", "http://disney.trendolizer.com/images/caption_14908343.jpg", "http://disney.trendolizer.com/images/288xNxcaption_14916507.jpg.pagespeed.ic.qIri760Zwq.jpg", "http://disney.trendolizer.com/images/288xNxcaption_14914957.jpg.pagespeed.ic.ftttIHuTGJ.jpg", "http://disney.trendolizer.com/images/288xNxcaption_14916665.jpg.pagespeed.ic.Vfiv1w6KVO.jpg", "http://disney.trendolizer.com/images/288xNxcaption_14908457.jpg.pagespeed.ic.SUrKX5uAXo.jpg", "http://disney.trendolizer.com/images/caption_14916341.jpg", "http://disney.trendolizer.com/images/288xNxcaption_14916414.jpg.pagespeed.ic.HbDsPPZ5Ht.jpg", "http://disney.trendolizer.com/images/caption_14914457.jpg", "http://disney.trendolizer.com/images/288xNxcaption_14916788.jpg.pagespeed.ic.KPg6usY_aY.jpg", "http://disney.trendolizer.com/images/288xNxcaption_14915707.jpg.pagespeed.ic.wCRiZEhmNF.jpg", "http://disney.trendolizer.com/images/caption_14910210.jpg", "http://disney.trendolizer.com/images/288xNxcaption_14909749.jpg.pagespeed.ic.XLov4sgGWO.jpg", "http://disney.trendolizer.com/images/caption_14915960.jpg", "http://www.trendolizer.com/opencalais.png", "http://disney.trendolizer.com/images/288xNxcaption_14907923.jpg.pagespeed.ic.889Z-RRUJ9.jpg", "http://disney.trendolizer.com/images/288xNxcaption_14908239.jpg.pagespeed.ic.T8dkzqTSep.jpg", "http://disney.trendolizer.com/images/caption_14914112.jpg", "http://disney.trendolizer.com/images/288xNxcaption_14910513.jpg.pagespeed.ic.28ikGbWYYB.jpg", "http://disney.trendolizer.com/images/288xNxcaption_14909476.jpg.pagespeed.ic.zpkV-9pxwP.jpg", "http://disney.trendolizer.com/images/288xNxcaption_14916073.jpg.pagespeed.ic.CDC9Ay12JK.jpg", "http://disney.trendolizer.com/images/288xNxcaption_14915519.jpg.pagespeed.ic.j-87NiJ4qC.jpg", "http://disney.trendolizer.com/images/288xNxcaption_14913516.jpg.pagespeed.ic.MSJhMpx7_U.jpg"], "top_img": "http://disney.trendolizer.com/images/caption_6898871.jpg", "keywords": [], "authors": ["Trending Story Found"], "canonical_link": "http://disney.trendolizer.com/2017/08/disney-channel-battle-vote-in-round-2-for-your-favorite-tv-series.html", "title": "Disney Channel Battle: Vote in Round 2 for Your Favorite TV Series", "meta_data": {"description": "Hannah Montana, Lizzie McGuire and That&#39;s So Raven are still in the running (via: trendolizer.com)", "apple-mobile-web-app-capable": "yes", "viewport": "width=device-width, user-scalable=no, initial-scale=1.0, maximum-scale=1.0, minimum-scale=1.0", "twitter": {"card": "summary", "site": "disneylizer"}, "og": {"title": "Disney Channel Battle: Vote in Round 2 for Your Favorite TV Series", "description": "Hannah Montana, Lizzie McGuire and That&#39;s So Raven are still in the running (via: trendolizer.com)", "type": "article", "url": "http://disney.trendolizer.com/2017/08/disney-channel-battle-vote-in-round-2-for-your-favorite-tv-series.html", "image": "http://disney.trendolizer.com/images/caption_6898871.jpg"}, "fb": {"app_id": 329363383802917, "admins": 759777462}, "google-site-verification": "uPd4PrEtsjZC8kPaqE_VMfUKydVQO3t6oQfznwjr3NM"}, "movies": [], "publish_date": null, "source": "http://disney.trendolizer.com", "summary": ""}