{"url": "https://www.hollywoodreporter.com/news/lin-manuel-mirandas-grandmother-dies-christmas-day-1070370", "text": "Lin-Manuel Miranda\u2019s maternal grandmother passed away on Christmas Day, according to the Grammy Award-winning playwright. Miranda took to Twitter to pay tribute to his late grandmother, Abuela Mundi.\n\n\u201cMy heart is in pieces and that\u2019s where it\u2019s gonna be for a bit,\u201d Miranda posted, along with black-and-white portraits of Mundi.\n\nMiranda had a close relationship with his grandmother, who even inspired the character Abuela Claudia in his musical In the Heights.\n\nAbuela Mundi passed away this Christmas morning. I may have more words in the days to come but for now my heart is in pieces and that\u2019s where it\u2019s gonna be for a bit. pic.twitter.com/f9Iia15Z9n \u2014 Lin-Manuel Miranda (@Lin_Manuel) December 26, 2017\n\nThis story first appeared on Billboard.com.", "images": ["https://www.hollywoodreporter.com/wp-content/uploads/2017/10/lin-manuel_miranda_getty_h_2017.jpg?w=1296&h=730&crop=1", "https://www.hollywoodreporter.com/wp-content/uploads/2017/10/lin-manuel_miranda_getty_h_2017.jpg?w=1024", "https://pixel.quantserve.com/pixel?a.1=&a.2=p-31f3D02tYU8zY", "https://sb.scorecardresearch.com/p?c1=2&c2=6035310&c3=&c4=&c5=&c6=&c15=&cv=2.0&cj=1", "https://cdn.shopify.com/s/files/1/0238/6647/products/2019_37_540x.jpg", "https://www.hollywoodreporter.com/wp-content/themes/vip/pmc-hollywoodreporter-2021/assets/public/lazyload-fallback.gif", "https://www.facebook.com/tr?id=352999048212581&ev=PageView&noscript=1"], "top_img": "https://www.hollywoodreporter.com/wp-content/uploads/2017/10/lin-manuel_miranda_getty_h_2017.jpg?w=1024", "keywords": [], "authors": ["Nina Braca Billboard"], "canonical_link": "https://www.hollywoodreporter.com/news/music-news/lin-manuel-mirandas-grandmother-dies-christmas-day-1070370/", "title": "Lin-Manuel Miranda\u2019s Grandmother Dies on Christmas Day", "meta_data": {"theme-color": "#fff", "viewport": "width=device-width, initial-scale=1.0", "description": "\"My heart is in pieces and that's where it's gonna be for a bit,\" the playwright wrote on Twitter.", "news_keywords": "Lin-Manuel Miranda", "robots": "max-image-preview:large", "generator": "WordPress 6.0.2", "author": "Nina Braca Billboard", "apple-mobile-web-app-capable": "yes", "mobile-web-app-capable": "yes", "apple-touch-fullscreen": "YES", "apple-mobile-web-app-title": "The Hollywood Reporter", "application-name": "The Hollywood Reporter", "content_type": "Article", "post_id": 1070370, "title": "Lin-Manuel Miranda's Grandmother Dies on Christmas Day", "published_at": "2017-12-26 13:26:16", "image": "https://www.hollywoodreporter.com/wp-content/uploads/2017/10/lin-manuel_miranda_getty_h_2017.jpg?w=1024", "comment_count": 0, "tags": "Lin-Manuel Miranda", "topics": "News", "body": "Lin-Manuel Miranda\u2019s maternal grandmother passed away on Christmas Day, according to the Grammy Award-winning playwright. Miranda took to Twitter to pay tribute to his late grandmother, Abuela Mundi.\r\n\u201cMy heart is in pieces and that's where it's gonna be for a bit,\u201d Miranda posted, along with black-and-white portraits of Mundi.\r\nMiranda had a close relationship with his grandmother, who even inspired the character Abuela Claudia in his musical\u00a0In the Heights.\r\n\r\n\tAbuela Mundi passed away this Christmas morning. I may have more words in the days to come but for now my heart is in pieces and that\u2019s where it\u2019s gonna be for a bit. pic.twitter.com/f9Iia15Z9n\r\n\t\u2014 Lin-Manuel Miranda (@Lin_Manuel) December 26, 2017\r\nThis story first appeared on\u00a0Billboard.com.", "fb": {"pages": 14425952749}, "fragment": "!", "og": {"type": "article", "title": "Lin-Manuel Miranda\u2019s Grandmother Dies on Christmas Day", "url": "https://www.hollywoodreporter.com/news/music-news/lin-manuel-mirandas-grandmother-dies-christmas-day-1070370/", "description": "\u201cMy heart is in pieces and that\u2019s where it\u2019s gonna be for a bit,\u201d the playwright wrote on Twitter.", "site_name": "The Hollywood Reporter", "image": {"identifier": "https://www.hollywoodreporter.com/wp-content/uploads/2017/10/lin-manuel_miranda_getty_h_2017.jpg?w=1024", "width": 1024, "height": 577}, "locale": "en_US"}, "article": {"published_time": "2017-12-26T13:26:16+00:00", "modified_time": "2017-12-27T02:20:16+00:00"}, "twitter": {"site": "@thr", "card": "summary_large_image", "title": "Lin-Manuel Miranda\u2019s Grandmother Dies on Christmas Day", "description": "\u201cMy heart is in pieces and that\u2019s where it\u2019s gonna be for a bit,\u201d the playwright wrote on Twitter.", "image": "https://www.hollywoodreporter.com/wp-content/uploads/2017/10/lin-manuel_miranda_getty_h_2017.jpg?w=1296"}}, "movies": [], "publish_date": 1514294776.0, "source": "https://www.hollywoodreporter.com", "summary": ""}