{"url": "https://www.newhot997.com/2018/05/24/jennifer-lopez-makes-the-real-housewives-look-poor-in-dinero/", "text": "Jennifer Lopez has it all in \u201cDinero\u201c\u2014designer clothes, expensive jewelry, Cardi B. In her new music video, directed by Joseph Kahn and featuring DJ Khaled, J.Lo does everything from burn money (and use it to make s\u2019mores) to take her pet ostrich for a walk. As one does, apparently!\n\nhttps://www.eonline.com/news/938704/jennifer-lopez-makes-the-real-housewives-look-poor-in-dinero", "images": ["https://khhk.b-cdn.net/site/wp-content/uploads/2022/09/hot40.png", "https://khhk.b-cdn.net/site/wp-content/themes/multinews/images/ajax-search-nav.png", "http://adserver.radioserversfive.com/www/delivery/avw.php?zoneid=170&cb=INSERT_RANDOM_NUMBER_HERE&n=a344871c", "https://khhk.b-cdn.net/site/wp-content/uploads/2022/09/hot180.png", "http://adserver.radioserversfive.com/www/delivery/avw.php?zoneid=171&cb=INSERT_RANDOM_NUMBER_HERE&n=adc3f7aa", "https://khhk.b-cdn.net/site/wp-content/themes/multinews/apple-touch-icon-precomposed.png"], "top_img": "https://khhk.b-cdn.net/site/wp-content/themes/multinews/apple-touch-icon-precomposed.png", "keywords": [], "authors": [], "canonical_link": "https://newhot997.com/khhk-homepage-news/jennifer-lopez-makes-the-real-housewives-look-poor-in-dinero/", "title": "Jennifer Lopez Makes the Real Housewives Look Poor in \u201cDinero\u201d", "meta_data": {"og": {"image": {"width": 960, "height": 547}, "title": "Jennifer Lopez Makes the Real Housewives Look Poor in \u201cDinero\u201d", "type": "article", "description": "Jennifer Lopez\u00a0has it all in \"Dinero\"\u2014designer clothes, expensive jewelry,\u00a0Cardi B. In her new music video, directed by\u00a0Joseph Kahn\u00a0and featuring\u00a0DJ Khaled, J.Lo does everything from burn money (and u", "url": "https://newhot997.com/khhk-homepage-news/jennifer-lopez-makes-the-real-housewives-look-poor-in-dinero/", "site_name": "Hot 99.7"}, "viewport": "width=device-width, initial-scale=1, maximum-scale=1", "robots": "max-image-preview:large", "generator": "Powered by WPBakery Page Builder - drag and drop page builder for WordPress."}, "movies": [], "publish_date": 1527116400.0, "source": "https://www.newhot997.com", "summary": ""}